greengraph/__init__.py
greengraph-0.0.0.dist-info/licenses/LICENSE.txt
greengraph-0.0.0.dist-info/METADATA
greengraph-0.0.0.dist-info/WHEEL
greengraph-0.0.0.dist-info/top_level.txt
greengraph-0.0.0.dist-info/RECORD
